	<!DOCTYPE r-pro>
	<r-pro version="1.0">
		<progname><!-- Имя программы --></progname>
		<comment><!-- Условный комментарий --></comment>
		<descriptive_part>
			<memory_block>
				<memory type="Register" name="reg1"/>
				<memory type="Register" name="Register"/>
				<memory type="Register" name="reg2"/>
				<memory type="Counter" name="ct1"/>
				<memory type="Counter" name="a"/>
				<memory type="Counter" name="b"/>
				<memory type="Wagon" leftName="W1LeftName" rightName="W1RightName"/>
			</memory_block>
			<alphabet>
				<abc name="Letter" short_name="L">Validation</abc>
				<abc name="Letter1" short_name="L1">descr1</abc>
			</alphabet>
		</descriptive_part>
		<alg>
			<arm begin = "0">
                <edge end = "1">
                    <predicate type="string">*</predicate>
					<operation>
						<left value = "123"/>
						<operator>-></operator>
						<right value ="a"/>
					</operation>
					<operation>
						<left value = "120"/>
						<operator>-></operator>
						<right value ="b"/>
					</operation>
                </edge>
			</arm>
			<arm begin ="1">
                <edge end = "2">
                    <predicate type="expression">
						<left value = "a"/>
						<sign>&gt;</sign>
						<right value = "b"/>
					</predicate>
					<operation>
						<left value =  "reg1"/>
						<operator>&lt;-</operator>
						<right value = "Hello World"/>
					</operation>
					<operation>
						<left value =  "reg2"/>
						<operator>&lt;-</operator>
						<right value = "reg1"/>
					</operation>
                </edge>
				<edge end = "3">
					<predicate type="string">predConst</predicate>
					<operation>
						<left value = "ct1"/>
						<operator>-&gt;</operator>
						<right value = "reg1"/>
					</operation>
					<operation>
						<left value =  "ct1"/>
						<operator>-&gt;</operator>
						<right value = "reg1"/>
					</operation>
				</edge>
				<edge end = "4">
					<predicate type="memory">reg1</predicate>
					<operation>
						<left value = "ct1"/>
						<operator>-&gt;</operator>
						<right value = "reg1"/>
					</operation>
				</edge>
            </arm>
			<arm begin = "2">
				<edge end = "4">
					<predicate type="alphabet">Letter</predicate>
					<operation>
						<left value = "42"/>
						<operator>-&gt;</operator>
						<right value ="a"/>
					</operation>
					<operation>
						<left value = "24"/>
						<operator>-&gt;</operator>
						<right value ="b"/>
					</operation>
				</edge>
				<edge end = "3">
					<predicate type="string">perfect</predicate>
					<operation>
						<left value = "42"/>
						<operator>-&gt;</operator>
						<right value ="a"/>
					</operation>
					<operation>
						<left value = "24"/>
						<operator>-&gt;</operator>
						<right value ="b"/>
					</operation>
				</edge>
			</arm>
			<arm begin = "3">
				<edge end = "11">
					<predicate type="alphabet">Letter</predicate>
					<operation>
						<left value = "42"/>
						<operator>-&gt;</operator>
						<right value ="a"/>
					</operation>
					<operation>
						<left value = "24"/>
						<operator>-&gt;</operator>
						<right value ="b"/>
					</operation>
				</edge>
				<edge end = "8">
					<predicate type="string">perfect</predicate>
					<operation>
						<left value = "42"/>
						<operator>-&gt;</operator>
						<right value ="a"/>
					</operation>
					<operation>
						<left value = "24"/>
						<operator>-&gt;</operator>
						<right value ="b"/>
					</operation>
				</edge>
			</arm>
		</alg>
	</r-pro>
